apyonics/__init__.py
apyonics/client.py
apyonics/plots.py
apyonics/substances_client.py
apyonics-0.3.2.dist-info/LICENSE
apyonics-0.3.2.dist-info/METADATA
apyonics-0.3.2.dist-info/WHEEL
apyonics-0.3.2.dist-info/top_level.txt
apyonics-0.3.2.dist-info/RECORD
