Metadata-Version: 2.1
Name: apyonics
Version: 0.3.2
Summary: Client for interacting with Aionics services
Home-page: https://github.com/aionics-io/apyonics
Author: Aionics
Author-email: support@aionics.io
License: UNKNOWN
Platform: UNKNOWN
Classifier: Programming Language :: Python :: 3
Classifier: License :: OSI Approved :: MIT License
Classifier: Operating System :: OS Independent
Requires-Python: >=3.5
Requires-Dist: requests
